vconfig_cli.py
vconfig_cli-0.1.0.dist-info/licenses/LICENSE
vconfig_cli-0.1.0.dist-info/METADATA
vconfig_cli-0.1.0.dist-info/WHEEL
vconfig_cli-0.1.0.dist-info/entry_points.txt
vconfig_cli-0.1.0.dist-info/top_level.txt
vconfig_cli-0.1.0.dist-info/RECORD
