Metadata-Version: 2.4
Name: vconfig-cli
Version: 0.1.0
Summary: vconfig wrapper for 'ip' to create vlans after deprecation of linux vconfig
Author-email: Liam Romanis <liamromanis101@btinternet.com>
License: MIT License
Project-URL: Homepage, https://github.com/liamromanis101/vconfig-cli
Project-URL: Issues, https://github.com/liamromanis101/vconfig-cli/issues
Keywords: vconfig,cli,vlan,ip
Classifier: Programming Language :: Python :: 3
Classifier: License :: OSI Approved :: MIT License
Requires-Python: >=3.8
License-File: LICENSE
Dynamic: license-file
